heavyedge_distance/__init__.py
heavyedge_distance/_dfd.cp311-win_amd64.pyd
heavyedge_distance/_dfd.pyx
heavyedge_distance/_wasserstein.cp311-win_amd64.pyd
heavyedge_distance/_wasserstein.pyx
heavyedge_distance/dfd.py
heavyedge_distance/wasserstein.py
heavyedge_distance/api/__init__.py
heavyedge_distance/api/distmat.py
heavyedge_distance/plugins/distmat.py
heavyedge_distance/samples/__init__.py
heavyedge_distance/samples/recipes.py
heavyedge_distance-1.0.0.dist-info/licenses/LICENSE
heavyedge_distance-1.0.0.dist-info/METADATA
heavyedge_distance-1.0.0.dist-info/WHEEL
heavyedge_distance-1.0.0.dist-info/entry_points.txt
heavyedge_distance-1.0.0.dist-info/top_level.txt
heavyedge_distance-1.0.0.dist-info/RECORD
